MANIFEST.in
README.rst
dispatch.conf
iplist.txt
setup.py
simpledns/__init__.py
simpledns/dnsproxy.py
simpledns/util.py
simpledns.egg-info/PKG-INFO
simpledns.egg-info/SOURCES.txt
simpledns.egg-info/dependency_links.txt
simpledns.egg-info/entry_points.txt
simpledns.egg-info/requires.txt
simpledns.egg-info/top_level.txt