Metadata-Version: 1.1
Name: simpledns
Version: 0.1.4
Summary: A lightweight yet useful proxy DNS server
Home-page: https://github.com/skyline75489/SimpleDNS
Author: skyline75489
Author-email: skyline75489@outlook.com
License: MIT
Platform: UNKNOWN
Classifier: License :: OSI Approved :: MIT License
Classifier: Operating System :: OS Independent
Classifier: Programming Language :: Python :: 2
Classifier: Programming Language :: Python :: 2.7
Classifier: Topic :: Internet :: Proxy Servers
